cflare_ddns/__init__.py
cflare_ddns/__main__.py
cflare_ddns/api.py
cflare_ddns/args.py
cflare_ddns/config.py
cflare_ddns/ddns.py
cflare_ddns/exceptions.py
cflare_ddns/ip.py
cflare_ddns/main.py
cflare_ddns-0.2.4.dist-info/LICENSE
cflare_ddns-0.2.4.dist-info/METADATA
cflare_ddns-0.2.4.dist-info/WHEEL
cflare_ddns-0.2.4.dist-info/entry_points.txt
cflare_ddns-0.2.4.dist-info/top_level.txt
cflare_ddns-0.2.4.dist-info/RECORD
