Metadata-Version: 2.1
Name: cflare-ddns
Version: 0.2.4
Summary: Yet another Cloudflare DDNS
Home-page: https://github.com/ianpogi5/cflare-ddns
Author: Ian Dela Cruz
Author-email: iandc76@gmail.com
Keywords: cloudflare,ddns,dynamic,dns
Classifier: Development Status :: 3 - Alpha
Classifier: Environment :: Console
Classifier: Intended Audience :: Developers
Classifier: Intended Audience :: Information Technology
Classifier: License :: OSI Approved :: MIT License
Classifier: Programming Language :: Python :: 3
Classifier: Operating System :: Unix
Classifier: Operating System :: MacOS :: MacOS X
Classifier: Operating System :: Microsoft :: Windows
Classifier: Topic :: Internet :: Name Service (DNS)
Classifier: Topic :: System :: Networking
License-File: LICENSE
Requires-Dist: requests >=2.31.0
